refx/__init__.py
refx/partitioning.py
refx/ref.py
refx/ref_field.py
refx/tracers.py
refx-0.0.3.dist-info/LICENSE
refx-0.0.3.dist-info/METADATA
refx-0.0.3.dist-info/WHEEL
refx-0.0.3.dist-info/RECORD
