Metadata-Version: 2.1
Name: refx
Version: 0.0.3
Summary: 
Author: Cristian Garcia
Author-email: cgarcia.e88@gmail.com
Requires-Python: >=3.8,<3.12
Classifier: Programming Language :: Python :: 3
Classifier: Programming Language :: Python :: 3.8
Classifier: Programming Language :: Python :: 3.9
Classifier: Programming Language :: Python :: 3.10
Classifier: Programming Language :: Python :: 3.11
Requires-Dist: jax (>=0.4.6)
